work_tracker/__init__.py
work_tracker/_work_tracker.py
work_tracker/checkpoint_manager.py
work_tracker/common.py
work_tracker/config.py
work_tracker/error.py
work_tracker/main.py
work_tracker/version.py
work_tracker/command/__init__.py
work_tracker/command/command_handler.py
work_tracker/command/command_history.py
work_tracker/command/command_initializer.py
work_tracker/command/command_manager.py
work_tracker/command/command_parser.py
work_tracker/command/command_query_handler.py
work_tracker/command/command_text_parser.py
work_tracker/command/common.py
work_tracker/command/macro_manager.py
work_tracker/command/commands/__date.py
work_tracker/command/commands/__macro.py
work_tracker/command/commands/__time.py
work_tracker/command/commands/block.py
work_tracker/command/commands/calculate.py
work_tracker/command/commands/calendar.py
work_tracker/command/commands/checkpoint.py
work_tracker/command/commands/clear.py
work_tracker/command/commands/config.py
work_tracker/command/commands/dayoff.py
work_tracker/command/commands/days.py
work_tracker/command/commands/deletemacro.py
work_tracker/command/commands/done.py
work_tracker/command/commands/end.py
work_tracker/command/commands/exit.py
work_tracker/command/commands/fte.py
work_tracker/command/commands/help.py
work_tracker/command/commands/history.py
work_tracker/command/commands/holiday.py
work_tracker/command/commands/info.py
work_tracker/command/commands/key.py
work_tracker/command/commands/macro.py
work_tracker/command/commands/minutes.py
work_tracker/command/commands/office.py
work_tracker/command/commands/recalculate.py
work_tracker/command/commands/redo.py
work_tracker/command/commands/remote.py
work_tracker/command/commands/rollback.py
work_tracker/command/commands/rwr.py
work_tracker/command/commands/setup.py
work_tracker/command/commands/start.py
work_tracker/command/commands/status.py
work_tracker/command/commands/target.py
work_tracker/command/commands/tutorial.py
work_tracker/command/commands/undo.py
work_tracker-0.1.3.dist-info/LICENSE
work_tracker-0.1.3.dist-info/METADATA
work_tracker-0.1.3.dist-info/WHEEL
work_tracker-0.1.3.dist-info/entry_points.txt
work_tracker-0.1.3.dist-info/top_level.txt
work_tracker-0.1.3.dist-info/RECORD
