Metadata-Version: 2.2
Name: work-tracker
Version: 0.1.3
Summary: A Python library that helps tracking your work time.
Author-email: Karol Kiszka <karolkisz22@gmail.com>
License: MIT
Project-URL: source, https://github.com/kiszkacy/work-tracker
Keywords: work,time,tracker
Classifier: Programming Language :: Python :: 3
Classifier: Programming Language :: Python :: 3.10
Classifier: Programming Language :: Python :: 3.11
Classifier: Programming Language :: Python :: 3.12
Classifier: Programming Language :: Python :: 3.13
Classifier: Development Status :: 3 - Alpha
Classifier: License :: OSI Approved :: MIT License
Classifier: Operating System :: OS Independent
Classifier: Environment :: Console
Requires-Python: <4.0,>=3.10
License-File: LICENSE
Requires-Dist: workalendar~=17.0.0
Requires-Dist: pydantic~=2.10.5
Requires-Dist: appdirs~=1.4.4
Requires-Dist: path~=17.1.0
Requires-Dist: PyYAML~=6.0.2
Requires-Dist: pyperclip~=1.9.0
Requires-Dist: colorama~=0.4.6
Requires-Dist: multimethod~=2.0
Requires-Dist: prompt_toolkit~=3.0.48
Provides-Extra: dev
Requires-Dist: pytest~=8.3.4; extra == "dev"
Requires-Dist: pytest-mock~=3.14.0; extra == "dev"
Requires-Dist: pytest-order~=1.3.0; extra == "dev"
Requires-Dist: pytest-random-order~=1.1.1; extra == "dev"
Requires-Dist: pytest-cov~=6.0.0; extra == "dev"
Requires-Dist: pexpect~=4.9.0; extra == "dev"
